vljepa/__init__.py
vljepa/main.py
vljepa-0.0.1a0.dist-info/licenses/LICENSE
vljepa-0.0.1a0.dist-info/METADATA
vljepa-0.0.1a0.dist-info/WHEEL
vljepa-0.0.1a0.dist-info/entry_points.txt
vljepa-0.0.1a0.dist-info/top_level.txt
vljepa-0.0.1a0.dist-info/RECORD
