Metadata-Version: 2.4
Name: vljepa
Version: 0.0.1a0
Summary: VL-JEPA (https://arxiv.org/abs/2512.10942)
Home-page: https://github.com/JosefAlbers/vljepa
Author: J Joe
Author-email: albersj66@gmail.com
License: Apache-2.0
License-File: LICENSE
Requires-Dist: mlx==0.30.1; platform_system == "Darwin"
Requires-Dist: transformers
Requires-Dist: datasets
Requires-Dist: numpy
Requires-Dist: Pillow
Provides-Extra: cuda
Requires-Dist: mlx[cuda]; extra == "cuda"
Provides-Extra: cpu
Requires-Dist: mlx[cpu]; extra == "cpu"
Provides-Extra: no-mlx
Dynamic: author
Dynamic: author-email
Dynamic: description
Dynamic: description-content-type
Dynamic: home-page
Dynamic: license
Dynamic: license-file
Dynamic: provides-extra
Dynamic: requires-dist
Dynamic: summary
